vectors/__init__.py
vectors/test_vectors.py
vectors/vectors.py
arturlib-0.0.1.dev2.dist-info/METADATA
arturlib-0.0.1.dev2.dist-info/WHEEL
arturlib-0.0.1.dev2.dist-info/top_level.txt
arturlib-0.0.1.dev2.dist-info/RECORD
